LICENSE.txt
pyproject.toml
setup.cfg
setup.py
pynoise/__init__.py
pynoise/colors.py
pynoise/gpu.py
pynoise/imaging.py
pynoise/interpolators.py
pynoise/noise.py
pynoise/noise_pics.py
pynoise/noisemodule.py
pynoise/noiseutil.py
pynoise/quality.py
pynoise/util.py
pynoise/vectortable.py
pynoise.egg-info/PKG-INFO
pynoise.egg-info/SOURCES.txt
pynoise.egg-info/dependency_links.txt
pynoise.egg-info/requires.txt
pynoise.egg-info/top_level.txt
tests/test_all.py
tests/test_renders.py