Metadata-Version: 2.4
Name: pynoise
Version: 3.0.0
Summary: An implementation of libnoise in python. Allows the creation of verious noise maps using a series of interconnected noise modules.
Home-page: https://gitlab.com/atrus6/pynoise
Download-URL: https://gitlab.com/atrus6/pynoise/repository/archive.tar.gz
Author: Tim Butram
Author-email: tim@timchi.me
Keywords: perlin,noise,procedural
Platform: any
License-File: LICENSE.txt
Requires-Dist: sortedcontainers>=0.9.6
Requires-Dist: pillow
Requires-Dist: numpy
Requires-Dist: pyopencl
Dynamic: author
Dynamic: author-email
Dynamic: download-url
Dynamic: home-page
Dynamic: keywords
Dynamic: license-file
Dynamic: platform
Dynamic: requires-dist
Dynamic: summary
